BAITS/__init__.py
BAITS/.ipynb_checkpoints/__init__-checkpoint.py
BAITS/VDJ/__init__.py
BAITS/VDJ/pl/__init__.py
BAITS/VDJ/pl/basic_plot.py
BAITS/VDJ/tl/__init__.py
BAITS/VDJ/tl/bcr_cluster.py
BAITS/VDJ/tl/bcr_desc.py
BAITS/VDJ/tl/qc.py
BAITS/VDJ/tl/summarize_BCR.py
BAITS/VDJ/tl/.ipynb_checkpoints/__init__-checkpoint.py
BAITS/VDJ/tl/.ipynb_checkpoints/bcr_cluster-checkpoint.py
BAITS/VDJ/tl/.ipynb_checkpoints/qc-checkpoint.py
BAITS/VDJ/tl/.ipynb_checkpoints/summarize_BCR-checkpoint.py
BAITS/st/__init__.py
BAITS/st/gr/__init__.py
BAITS/st/gr/_aggr.py
BAITS/st/gr/_build_spatial_adj.py
BAITS/st/gr/_get_adj.py
BAITS/st/gr/_utils.py
BAITS/st/gr/.ipynb_checkpoints/__init__-checkpoint.py
BAITS/st/gr/.ipynb_checkpoints/_aggr-checkpoint.py
BAITS/st/gr/.ipynb_checkpoints/_build_spatial_adj-checkpoint.py
BAITS/st/gr/.ipynb_checkpoints/_get_adj-checkpoint.py
BAITS/st/gr/.ipynb_checkpoints/_utils-checkpoint.py
BAITS/st/pl/__init__.py
BAITS/st/pl/_clustering_results.py
BAITS/st/pl/_enrichment_score.py
BAITS/st/pl/_kde_filter.py
BAITS/st/pl/_silhouette_score.py
BAITS/st/pl/.ipynb_checkpoints/__init__-checkpoint.py
BAITS/st/pl/.ipynb_checkpoints/_clustering_results-checkpoint.py
BAITS/st/pl/.ipynb_checkpoints/_enrichment_score-checkpoint.py
BAITS/st/pl/.ipynb_checkpoints/_kde_filter-checkpoint.py
BAITS/st/pl/.ipynb_checkpoints/_silhouette_score-checkpoint.py
BAITS/st/tl/_GMM.py
BAITS/st/tl/__init__.py
BAITS/st/tl/_batch_process.py
BAITS/st/tl/_cluster_Auto_k.py
BAITS/st/tl/_dbscan_cluster.py
BAITS/st/tl/_kde_filter.py
BAITS/st/tl/.ipynb_checkpoints/_GMM-checkpoint.py
BAITS/st/tl/.ipynb_checkpoints/__init__-checkpoint.py
BAITS/st/tl/.ipynb_checkpoints/_batch_process-checkpoint.py
BAITS/st/tl/.ipynb_checkpoints/_cluster_Auto_k-checkpoint.py
BAITS/st/tl/.ipynb_checkpoints/_dbscan_cluster-checkpoint.py
BAITS/st/tl/.ipynb_checkpoints/_kde_filter-checkpoint.py
baits-0.1.dist-info/METADATA
baits-0.1.dist-info/WHEEL
baits-0.1.dist-info/licenses/LICENSE
baits-0.1.dist-info/RECORD
